__init__.py
DA4RDM_Vis_VectorBased/Evaluate.py
DA4RDM_Vis_VectorBased/Extract.py
DA4RDM_Vis_VectorBased/Timestamp.py
DA4RDM_Vis_VectorBased/Visualize.py
DA4RDM_Vis_VectorBased/__init__.py
DA4RDM_Vis_VectorBased-0.1.1.dist-info/LICENSE
DA4RDM_Vis_VectorBased-0.1.1.dist-info/METADATA
DA4RDM_Vis_VectorBased-0.1.1.dist-info/WHEEL
DA4RDM_Vis_VectorBased-0.1.1.dist-info/top_level.txt
DA4RDM_Vis_VectorBased-0.1.1.dist-info/RECORD
