Metadata-Version: 2.1
Name: DA4RDM-Vis-VectorBased
Version: 0.1.1
Summary: Package that can be used to perform RDLC analysis by determining the correlations for the different phases of the development life cycle.
Classifier: Programming Language :: Python :: 3
Classifier: License :: OSI Approved :: MIT License
Classifier: Operating System :: OS Independent
Requires-Python: >=3.7
License-File: LICENSE
Requires-Dist: plotly (>=5.8.2)
Requires-Dist: numpy (>=1.18.1)
Requires-Dist: pandas (>=1.0.1)
Requires-Dist: python-dateutil (>=2.8.2)
Requires-Dist: scipy (>=1.4.1)
Requires-Dist: kaleido (>=0.2.1)
